LICENSE.txt
MANIFEST.in
README.md
setup.cfg
setup.py
bol/__init__.py
bol/api.py
bol/cachehandler.py
bol/config.py
bol/cache/__init__.py
bol/constants/reasons.py
bol/constants/transporters.py
bol/endpoints/__init__.py
bol/endpoints/base.py
bol/endpoints/orders.py
bol/endpoints/processes.py
bol/endpoints/shippinglabels.py
bol/models/__init__.py
bol/models/base.py
bol/models/errors.py
bol/models/orders.py
bol/models/processes.py
bol/models/shippinglabels.py
bol/models/transports.py
python_bol_retailer_api.egg-info/PKG-INFO
python_bol_retailer_api.egg-info/SOURCES.txt
python_bol_retailer_api.egg-info/dependency_links.txt
python_bol_retailer_api.egg-info/requires.txt
python_bol_retailer_api.egg-info/top_level.txt